pyCausalFS/__init__.py
pyCausalFS/CBD/__init__.py
pyCausalFS/CBD/MBs/BAMB.py
pyCausalFS/CBD/MBs/FBEDk.py
pyCausalFS/CBD/MBs/GSMB.py
pyCausalFS/CBD/MBs/IAMB.py
pyCausalFS/CBD/MBs/IAMBnPC.py
pyCausalFS/CBD/MBs/KIAMB.py
pyCausalFS/CBD/MBs/LCMB.py
pyCausalFS/CBD/MBs/MBOR.py
pyCausalFS/CBD/MBs/STMB.py
pyCausalFS/CBD/MBs/__init__.py
pyCausalFS/CBD/MBs/fast_IAMB.py
pyCausalFS/CBD/MBs/interIAMBnPC.py
pyCausalFS/CBD/MBs/inter_IAMB.py
pyCausalFS/CBD/MBs/pc_simple.py
pyCausalFS/CBD/MBs/HITON/HITON_MB.py
pyCausalFS/CBD/MBs/HITON/HITON_PC.py
pyCausalFS/CBD/MBs/HITON/__init__.py
pyCausalFS/CBD/MBs/IPCMB/IPCMB.py
pyCausalFS/CBD/MBs/IPCMB/RecognizePC.py
pyCausalFS/CBD/MBs/IPCMB/__init__.py
pyCausalFS/CBD/MBs/MMMB/MMMB.py
pyCausalFS/CBD/MBs/MMMB/MMPC.py
pyCausalFS/CBD/MBs/MMMB/__init__.py
pyCausalFS/CBD/MBs/PCMB/PCMB.py
pyCausalFS/CBD/MBs/PCMB/__init__.py
pyCausalFS/CBD/MBs/PCMB/getPC.py
pyCausalFS/CBD/MBs/TIE_star/IAMB.py
pyCausalFS/CBD/MBs/TIE_star/TIEs.py
pyCausalFS/CBD/MBs/TIE_star/__init__.py
pyCausalFS/CBD/MBs/TIE_star/eva_classifier.py
pyCausalFS/CBD/MBs/common/Meek.py
pyCausalFS/CBD/MBs/common/__init__.py
pyCausalFS/CBD/MBs/common/chi_square_test.py
pyCausalFS/CBD/MBs/common/condition_independence_test.py
pyCausalFS/CBD/MBs/common/fisher_z_test.py
pyCausalFS/CBD/MBs/common/g2test.py
pyCausalFS/CBD/MBs/common/optimalnetwork.py
pyCausalFS/CBD/MBs/common/realMB.py
pyCausalFS/CBD/MBs/common/real_MB.py
pyCausalFS/CBD/MBs/common/subsets.py
pyCausalFS/CBD/MBs/common/tocsv.py
pyCausalFS/CBD/MBs/semi_HITON/__init__.py
pyCausalFS/CBD/MBs/semi_HITON/semi_HITON_MB.py
pyCausalFS/CBD/MBs/semi_HITON/semi_HITON_PC.py
pyCausalFS/GSL/GSBN.py
pyCausalFS/GSL/MBGSL.py
pyCausalFS/GSL/P-C.py
pyCausalFS/GSL/__init__.py
pyCausalFS/GSL/MMHC/MMHC.py
pyCausalFS/GSL/MMHC/__init__.py
pyCausalFS/GSL/MMHC/accessory.py
pyCausalFS/GSL/MMHC/evaluation.py
pyCausalFS/GSL/MMHC/hc.py
pyCausalFS/GSL/common/__init__.py
pyCausalFS/GSL/common/real_P_C_S.py
pyCausalFS/LSL/__init__.py
pyCausalFS-0.23.dist-info/LICENSE
pyCausalFS-0.23.dist-info/METADATA
pyCausalFS-0.23.dist-info/WHEEL
pyCausalFS-0.23.dist-info/top_level.txt
pyCausalFS-0.23.dist-info/RECORD
