Metadata-Version: 2.1
Name: pyCausalFS
Version: 0.23
Summary: Fork of pyCausalFS - implementation of local structure learning algorithms
Home-page: https://github.com/chris-tran-16/pyCausalFS
Author: Christopher Tran
Author-email: ctran29@uic.edu
License: UNKNOWN
Platform: UNKNOWN
Classifier: Programming Language :: Python :: 3
Classifier: License :: OSI Approved :: GNU General Public License v3 (GPLv3)
Classifier: Operating System :: OS Independent
Requires-Python: >=3.6
License-File: LICENSE
Requires-Dist: numpy
Requires-Dist: pandas
Requires-Dist: scipy
Requires-Dist: scikit-learn
Requires-Dist: networkx
Requires-Dist: matplotlib
